lapinmq/__init__.py
lapinmq/consumer.py
lapinmq/message.py
lapinmq/publisher.py
lapinmq/utils.py
lapinmq-0.1.1.dist-info/METADATA
lapinmq-0.1.1.dist-info/WHEEL
lapinmq-0.1.1.dist-info/top_level.txt
lapinmq-0.1.1.dist-info/RECORD
