Metadata-Version: 2.1
Name: lapinmq
Version: 0.1.1
Summary: Utilities for RabbitMQ following best practices
Home-page: https://github.com/madhur-tandon/lapinmq
Author: Madhur Tandon
Author-email: madhurtandon23@gmail.com
License: BSD 2-clause
Classifier: Programming Language :: Python :: 3
Classifier: License :: OSI Approved :: MIT License
Classifier: Operating System :: OS Independent
Requires-Dist: pika ==1.3.2
